dashscope/__init__.py
dashscope/cli.py
dashscope/files.py
dashscope/model.py
dashscope/models.py
dashscope/version.py
dashscope/aigc/__init__.py
dashscope/aigc/chat_completion.py
dashscope/aigc/code_generation.py
dashscope/aigc/conversation.py
dashscope/aigc/generation.py
dashscope/aigc/image_generation.py
dashscope/aigc/image_synthesis.py
dashscope/aigc/multimodal_conversation.py
dashscope/aigc/video_synthesis.py
dashscope/api_entities/__init__.py
dashscope/api_entities/aiohttp_request.py
dashscope/api_entities/api_request_data.py
dashscope/api_entities/api_request_factory.py
dashscope/api_entities/base_request.py
dashscope/api_entities/chat_completion_types.py
dashscope/api_entities/dashscope_response.py
dashscope/api_entities/encryption.py
dashscope/api_entities/http_request.py
dashscope/api_entities/websocket_request.py
dashscope/app/__init__.py
dashscope/app/application.py
dashscope/app/application_response.py
dashscope/assistants/__init__.py
dashscope/assistants/assistant_types.py
dashscope/assistants/assistants.py
dashscope/assistants/files.py
dashscope/audio/__init__.py
dashscope/audio/asr/__init__.py
dashscope/audio/asr/asr_phrase_manager.py
dashscope/audio/asr/recognition.py
dashscope/audio/asr/transcription.py
dashscope/audio/asr/translation_recognizer.py
dashscope/audio/asr/vocabulary.py
dashscope/audio/qwen_asr/__init__.py
dashscope/audio/qwen_asr/qwen_transcription.py
dashscope/audio/qwen_omni/__init__.py
dashscope/audio/qwen_omni/omni_realtime.py
dashscope/audio/qwen_tts/__init__.py
dashscope/audio/qwen_tts/speech_synthesizer.py
dashscope/audio/qwen_tts_realtime/__init__.py
dashscope/audio/qwen_tts_realtime/qwen_tts_realtime.py
dashscope/audio/tts/__init__.py
dashscope/audio/tts/speech_synthesizer.py
dashscope/audio/tts_v2/__init__.py
dashscope/audio/tts_v2/enrollment.py
dashscope/audio/tts_v2/speech_synthesizer.py
dashscope/client/__init__.py
dashscope/client/base_api.py
dashscope/common/__init__.py
dashscope/common/api_key.py
dashscope-1.25.9.dist-info/licenses/LICENSE
dashscope-1.25.9.dist-info/METADATA
dashscope-1.25.9.dist-info/WHEEL
dashscope-1.25.9.dist-info/entry_points.txt
dashscope-1.25.9.dist-info/top_level.txt
dashscope-1.25.9.dist-info/RECORD
