Metadata-Version: 2.4
Name: dashscope
Version: 1.25.9
Summary: dashscope client sdk library
Home-page: https://dashscope.aliyun.com/
Author: Alibaba Cloud
Author-email: dashscope@alibabacloud.com
License: Apache 2.0
Platform: Posix; MacOS X; Windows
Classifier: Development Status :: 4 - Beta
Classifier: Intended Audience :: Developers
Classifier: License :: OSI Approved :: Apache Software License
Classifier: Programming Language :: Python
Classifier: Programming Language :: Python :: 3
Classifier: Programming Language :: Python :: 3.8
Classifier: Programming Language :: Python :: 3.9
Classifier: Programming Language :: Python :: 3.10
Classifier: Programming Language :: Python :: 3.11
Requires-Python: >=3.8.0
License-File: LICENSE
Requires-Dist: aiohttp
Requires-Dist: requests
Requires-Dist: websocket-client
Requires-Dist: cryptography
Requires-Dist: certifi
Provides-Extra: tokenizer
Requires-Dist: tiktoken; extra == "tokenizer"
Dynamic: author
Dynamic: author-email
Dynamic: classifier
Dynamic: description
Dynamic: description-content-type
Dynamic: home-page
Dynamic: license
Dynamic: license-file
Dynamic: platform
Dynamic: provides-extra
Dynamic: requires-dist
Dynamic: requires-python
Dynamic: summary
